hmmlogo/__init__.py
hmmlogo/alph.json
hmmlogo/api.py
hmmlogo/cmap.json
hmmlogo/exceptions.py
hmmlogo/hmm.py
hmmlogo/plot.py
hmmlogo-0.0.4.dist-info/LICENSE
hmmlogo-0.0.4.dist-info/METADATA
hmmlogo-0.0.4.dist-info/WHEEL
hmmlogo-0.0.4.dist-info/top_level.txt
hmmlogo-0.0.4.dist-info/RECORD
