Metadata-Version: 2.1
Name: hmmlogo
Version: 0.0.4
Summary: Package to plot logos for profile hidden Markov models.
Home-page: https://github.com/imyp/hmmlogo
Author: Inti Manuel Yabar-Pagaza
Author-email: intipagaza@live.dk
License: UNKNOWN
Platform: UNKNOWN
Classifier: Programming Language :: Python :: 3
Classifier: License :: OSI Approved :: MIT License
Classifier: Operating System :: OS Independent
Requires-Python: >=3.6
Requires-Dist: matplotlib
Requires-Dist: requests
Requires-Dist: pandas
Requires-Dist: numpy
